{
  "timestamp": "2025-10-17T13:41:31.835266",
  "date": "2025-10-17",
  "scan_log": [
    "================================================================================",
    "NASDAQ 100 FORWARD VOLATILITY SCANNER",
    "================================================================================",
    "",
    "Scanning: 104 NASDAQ 100 stocks",
    "Threshold: 0.2",
    ""
  ],
  "opportunities": [
    {
      "ticker": "ADSK",
      "price": 303.66,
      "expiry1": "20251024",
      "expiry2": "20251031",
      "dte1": 6,
      "dte2": 13,
      "ff_call": 0.242,
      "ff_put": 0.242,
      "ff_avg": 0.242,
      "best_ff": 0.242,
      "next_earnings": "2025-11-21",
      "call_iv1": 30.78,
      "call_iv2": 27.72,
      "put_iv1": 30.78,
      "put_iv2": 27.72,
      "avg_iv1": 30.78,
      "avg_iv2": 27.72,
      "trade_details": {
        "spread_type": "PUT",
        "strike": 302.5,
        "front_iv": 30.78,
        "back_iv": 27.72,
        "ff_display": 0.242,
        "front_price": 4.793418939198913,
        "back_price": 6.3542756234720095,
        "net_debit": 1.5608566842730962,
        "net_debit_total": 156.08566842730963,
        "best_case": 62.434267370923855,
        "typical_case": 31.217133685461928,
        "adverse_case": -46.82570052819288,
        "max_loss": -156.08566842730963,
        "best_case_pct": 40.00000000000001,
        "typical_case_pct": 20.000000000000004,
        "adverse_case_pct": -30.0,
        "max_loss_pct": -100.0
      }
    },
    {
      "ticker": "ALGN",
      "price": 130.75,
      "expiry1": "20251031",
      "expiry2": "20251107",
      "dte1": 13,
      "dte2": 20,
      "ff_call": 0.882,
      "ff_put": 0.882,
      "ff_avg": 0.882,
      "best_ff": 0.882,
      "next_earnings": null,
      "call_iv1": 82.92,
      "call_iv2": 71.76,
      "put_iv1": 82.92,
      "put_iv2": 71.76,
      "avg_iv1": 82.92,
      "avg_iv2": 71.76,
      "trade_details": {
        "spread_type": "PUT",
        "strike": 130.0,
        "front_iv": 82.92,
        "back_iv": 71.76,
        "ff_display": 0.882,
        "front_price": 8.184388306789279,
        "back_price": 8.785220868042869,
        "net_debit": 0.6008325612535899,
        "net_debit_total": 60.083256125358986,
        "best_case": 24.033302450143594,
        "typical_case": 12.016651225071797,
        "adverse_case": -18.024976837607696,
        "max_loss": -60.083256125358986,
        "best_case_pct": 40.0,
        "typical_case_pct": 20.0,
        "adverse_case_pct": -30.0,
        "max_loss_pct": -100.0
      }
    },
    {
      "ticker": "ALGN",
      "price": 130.75,
      "expiry1": "20251107",
      "expiry2": "20251114",
      "dte1": 20,
      "dte2": 27,
      "ff_call": 0.622,
      "ff_put": null,
      "ff_avg": 0.343,
      "best_ff": 0.622,
      "next_earnings": null,
      "call_iv1": 85.88,
      "call_iv2": 78.68,
      "put_iv1": 81.43,
      "put_iv2": null,
      "avg_iv1": 83.66,
      "avg_iv2": 78.68,
      "trade_details": {
        "spread_type": "CALL",
        "strike": 130.0,
        "front_iv": 85.88,
        "back_iv": 78.68,
        "ff_display": 0.622,
        "front_price": 10.513862432379064,
        "back_price": 11.191839927020606,
        "net_debit": 0.6779774946415422,
        "net_debit_total": 67.79774946415422,
        "best_case": 27.11909978566169,
        "typical_case": 13.559549892830844,
        "adverse_case": -20.339324839246267,
        "max_loss": -67.79774946415422,
        "best_case_pct": 40.0,
        "typical_case_pct": 20.0,
        "adverse_case_pct": -30.0,
        "max_loss_pct": -100.0
      }
    },
    {
      "ticker": "CSX",
      "price": 36.95,
      "expiry1": "20251107",
      "expiry2": "20251114",
      "dte1": 20,
      "dte2": 27,
      "ff_call": 1.172,
      "ff_put": -0.107,
      "ff_avg": 0.216,
      "best_ff": 1.172,
      "next_earnings": null,
      "call_iv1": 24.67,
      "call_iv2": 22.01,
      "put_iv1": 21.32,
      "put_iv2": 22.01,
      "avg_iv1": 23.0,
      "avg_iv2": 22.01,
      "trade_details": {
        "spread_type": "CALL",
        "strike": 37.5,
        "front_iv": 24.67,
        "back_iv": 22.01,
        "ff_display": 1.172,
        "front_price": 0.8535169479527168,
        "back_price": 0.88476905863848,
        "net_debit": 0.03125211068576317,
        "net_debit_total": 3.125211068576317,
        "best_case": 1.2500844274305267,
        "typical_case": 0.6250422137152634,
        "adverse_case": -0.937563320572895,
        "max_loss": -3.125211068576317,
        "best_case_pct": 40.0,
        "typical_case_pct": 20.0,
        "adverse_case_pct": -30.0,
        "max_loss_pct": -100.0
      }
    },
    {
      "ticker": "INTC",
      "price": 37.03,
      "expiry1": "20251024",
      "expiry2": "20251031",
      "dte1": 6,
      "dte2": 13,
      "ff_call": 0.562,
      "ff_put": 0.562,
      "ff_avg": 0.562,
      "best_ff": 0.562,
      "next_earnings": "2025-10-31",
      "call_iv1": 109.98,
      "call_iv2": 90.84,
      "put_iv1": 109.98,
      "put_iv2": 90.84,
      "avg_iv1": 109.98,
      "avg_iv2": 90.84,
      "trade_details": {
        "spread_type": "PUT",
        "strike": 37.5,
        "front_iv": 109.98000000000002,
        "back_iv": 90.84,
        "ff_display": 0.562,
        "front_price": 2.088606434782695,
        "back_price": 2.539312045815033,
        "net_debit": 0.45070561103233775,
        "net_debit_total": 45.07056110323377,
        "best_case": 18.02822444129351,
        "typical_case": 9.014112220646755,
        "adverse_case": -13.521168330970132,
        "max_loss": -45.07056110323377,
        "best_case_pct": 40.0,
        "typical_case_pct": 20.0,
        "adverse_case_pct": -30.0,
        "max_loss_pct": -100.0
      }
    },
    {
      "ticker": "INTC",
      "price": 37.03,
      "expiry1": "20251031",
      "expiry2": "20251107",
      "dte1": 13,
      "dte2": 20,
      "ff_call": 0.301,
      "ff_put": 0.301,
      "ff_avg": 0.301,
      "best_ff": 0.301,
      "next_earnings": "2025-10-31",
      "call_iv1": 90.84,
      "call_iv2": 84.08,
      "put_iv1": 90.84,
      "put_iv2": 84.08,
      "avg_iv1": 90.84,
      "avg_iv2": 84.08,
      "trade_details": {
        "spread_type": "PUT",
        "strike": 37.5,
        "front_iv": 90.84,
        "back_iv": 84.08,
        "ff_display": 0.301,
        "front_price": 2.539312045815033,
        "back_price": 2.915244414967695,
        "net_debit": 0.3759323691526619,
        "net_debit_total": 37.59323691526619,
        "best_case": 15.037294766106479,
        "typical_case": 7.518647383053239,
        "adverse_case": -11.277971074579856,
        "max_loss": -37.59323691526619,
        "best_case_pct": 40.00000000000001,
        "typical_case_pct": 20.000000000000004,
        "adverse_case_pct": -30.0,
        "max_loss_pct": -100.0
      }
    },
    {
      "ticker": "ISRG",
      "price": 446.13,
      "expiry1": "20251031",
      "expiry2": "20251107",
      "dte1": 13,
      "dte2": 20,
      "ff_call": 1.075,
      "ff_put": null,
      "ff_avg": 0.552,
      "best_ff": 1.075,
      "next_earnings": null,
      "call_iv1": 59.02,
      "call_iv2": 50.47,
      "put_iv1": 54.16,
      "put_iv2": null,
      "avg_iv1": 56.59,
      "avg_iv2": 50.47,
      "trade_details": {
        "spread_type": "CALL",
        "strike": 445.0,
        "front_iv": 59.02,
        "back_iv": 50.470000000000006,
        "ff_display": 1.075,
        "front_price": 19.87677257964527,
        "back_price": 21.082557331358664,
        "net_debit": 1.205784751713395,
        "net_debit_total": 120.5784751713395,
        "best_case": 48.23139006853581,
        "typical_case": 24.115695034267905,
        "adverse_case": -36.17354255140185,
        "max_loss": -120.5784751713395,
        "best_case_pct": 40.0,
        "typical_case_pct": 20.0,
        "adverse_case_pct": -30.0,
        "max_loss_pct": -100.0
      }
    },
    {
      "ticker": "LCID",
      "price": 19.72,
      "expiry1": "20251107",
      "expiry2": "20251114",
      "dte1": 20,
      "dte2": 27,
      "ff_call": 1.047,
      "ff_put": 0.152,
      "ff_avg": 0.442,
      "best_ff": 1.047,
      "next_earnings": "2025-11-07",
      "call_iv1": 101.1,
      "call_iv2": 90.58,
      "put_iv1": 93.62,
      "put_iv2": 90.58,
      "avg_iv1": 97.36,
      "avg_iv2": 90.58,
      "trade_details": {
        "spread_type": "CALL",
        "strike": 20.0,
        "front_iv": 101.1,
        "back_iv": 90.58,
        "ff_display": 1.047,
        "front_price": 1.866751990685983,
        "back_price": 1.9432768102783362,
        "net_debit": 0.07652481959235313,
        "net_debit_total": 7.652481959235313,
        "best_case": 3.0609927836941253,
        "typical_case": 1.5304963918470627,
        "adverse_case": -2.295744587770594,
        "max_loss": -7.652481959235313,
        "best_case_pct": 40.0,
        "typical_case_pct": 20.0,
        "adverse_case_pct": -30.0,
        "max_loss_pct": -100.0
      }
    },
    {
      "ticker": "MELI",
      "price": 2030.0,
      "expiry1": "20251107",
      "expiry2": "20251114",
      "dte1": 20,
      "dte2": 27,
      "ff_call": 1.094,
      "ff_put": 0.501,
      "ff_avg": 0.732,
      "best_ff": 1.094,
      "next_earnings": "2025-11-07",
      "call_iv1": 60.01,
      "call_iv2": 53.67,
      "put_iv1": 58.02,
      "put_iv2": 53.67,
      "avg_iv1": 59.01,
      "avg_iv2": 53.67,
      "trade_details": {
        "spread_type": "CALL",
        "strike": 2030.0,
        "front_iv": 60.01,
        "back_iv": 53.67000000000001,
        "ff_display": 1.094,
        "front_price": 114.06390131021425,
        "back_price": 118.52857806123095,
        "net_debit": 4.464676751016697,
        "net_debit_total": 446.46767510166967,
        "best_case": 178.58707004066787,
        "typical_case": 89.29353502033393,
        "adverse_case": -133.9403025305009,
        "max_loss": -446.46767510166967,
        "best_case_pct": 40.0,
        "typical_case_pct": 20.0,
        "adverse_case_pct": -30.0,
        "max_loss_pct": -100.0
      }
    },
    {
      "ticker": "MELI",
      "price": 2030.0,
      "expiry1": "20251031",
      "expiry2": "20251107",
      "dte1": 13,
      "dte2": 20,
      "ff_call": 0.366,
      "ff_put": null,
      "ff_avg": 0.16,
      "best_ff": 0.366,
      "next_earnings": "2025-11-07",
      "call_iv1": 63.04,
      "call_iv2": 57.69,
      "put_iv1": 57.9,
      "put_iv2": null,
      "avg_iv1": 60.47,
      "avg_iv2": 57.69,
      "trade_details": {
        "spread_type": "CALL",
        "strike": 2030.0,
        "front_iv": 63.04,
        "back_iv": 57.69,
        "ff_display": 0.366,
        "front_price": 96.60452682497926,
        "back_price": 109.65416541553509,
        "net_debit": 13.04963859055583,
        "net_debit_total": 1304.963859055583,
        "best_case": 521.9855436222332,
        "typical_case": 260.9927718111166,
        "adverse_case": -391.48915771667487,
        "max_loss": -1304.963859055583,
        "best_case_pct": 40.0,
        "typical_case_pct": 20.0,
        "adverse_case_pct": -30.0,
        "max_loss_pct": -100.0
      }
    },
    {
      "ticker": "WBD",
      "price": 18.21,
      "expiry1": "20251107",
      "expiry2": "20251114",
      "dte1": 20,
      "dte2": 27,
      "ff_call": 0.64,
      "ff_put": 0.256,
      "ff_avg": 0.415,
      "best_ff": 0.64,
      "next_earnings": "2025-11-07",
      "call_iv1": 77.29,
      "call_iv2": 70.72,
      "put_iv1": 74.33,
      "put_iv2": 70.72,
      "avg_iv1": 75.81,
      "avg_iv2": 70.72,
      "trade_details": {
        "spread_type": "CALL",
        "strike": 17.5,
        "front_iv": 77.29,
        "back_iv": 70.72,
        "ff_display": 0.64,
        "front_price": 1.3178373436658115,
        "back_price": 1.4010306585063022,
        "net_debit": 0.08319331484049064,
        "net_debit_total": 8.319331484049064,
        "best_case": 3.3277325936196256,
        "typical_case": 1.6638662968098128,
        "adverse_case": -2.495799445214719,
        "max_loss": -8.319331484049064,
        "best_case_pct": 40.0,
        "typical_case_pct": 20.0,
        "adverse_case_pct": -30.0,
        "max_loss_pct": -100.0
      }
    },
    {
      "ticker": "ZS",
      "price": 300.25,
      "expiry1": "20251107",
      "expiry2": "20251114",
      "dte1": 20,
      "dte2": 27,
      "ff_call": 0.272,
      "ff_put": 0.141,
      "ff_avg": 0.202,
      "best_ff": 0.272,
      "next_earnings": "2025-12-03",
      "call_iv1": 42.67,
      "call_iv2": 40.5,
      "put_iv1": 41.78,
      "put_iv2": 40.5,
      "avg_iv1": 42.22,
      "avg_iv2": 40.5,
      "trade_details": {
        "spread_type": "CALL",
        "strike": 300.0,
        "front_iv": 42.67,
        "back_iv": 40.5,
        "ff_display": 0.272,
        "front_price": 11.995938093563058,
        "back_price": 13.229196901121027,
        "net_debit": 1.2332588075579682,
        "net_debit_total": 123.32588075579682,
        "best_case": 49.33035230231873,
        "typical_case": 24.665176151159365,
        "adverse_case": -36.997764226739044,
        "max_loss": -123.32588075579682,
        "best_case_pct": 40.0,
        "typical_case_pct": 20.0,
        "adverse_case_pct": -30.0,
        "max_loss_pct": -100.0
      }
    }
  ],
  "summary": {
    "total_opportunities": 12,
    "tickers_scanned": 104,
    "best_ff": 1.172,
    "avg_ff": 0.6895833333333332
  }
}